gurglefish/DriverManager.py
gurglefish/FileManager.py
gurglefish/__init__.py
gurglefish/__main__.py
gurglefish/config.py
gurglefish/context.py
gurglefish/logging.yml
gurglefish/schema.py
gurglefish/sfapi.py
gurglefish/sfarchive.py
gurglefish/sfexport.py
gurglefish/sfimport.py
gurglefish/tools.py
gurglefish/transformutils.py
gurglefish/drivers/__init__.py
gurglefish/drivers/postgresql/Driver.py
gurglefish/drivers/postgresql/__init__.py
gurglefish/objects/__init__.py
gurglefish/objects/connections.py
gurglefish/objects/files.py
gurglefish/objects/sobject.py
gurglefish-1.1.9.dist-info/LICENSE
gurglefish-1.1.9.dist-info/METADATA
gurglefish-1.1.9.dist-info/WHEEL
gurglefish-1.1.9.dist-info/entry_points.txt
gurglefish-1.1.9.dist-info/top_level.txt
gurglefish-1.1.9.dist-info/RECORD
