Metadata-Version: 2.1
Name: gurglefish
Version: 1.1.9
Summary: Sync and maintain Salesforce sobjects in a Postgres database
Home-page: https://github.com/mlsmithjr/gurglefish
Author: Marshall L Smith Jr
Author-email: marshallsmithjr@gmail.com
License: UNKNOWN
Keywords: salesforce sobject database synchronization snapshots postgres postgresql
Platform: UNKNOWN
Classifier: Programming Language :: Python :: 3
Classifier: Environment :: Console
Classifier: Topic :: Database
Classifier: License :: OSI Approved :: GNU General Public License v3 (GPLv3)
Classifier: Intended Audience :: System Administrators
Classifier: Natural Language :: English
Classifier: Operating System :: POSIX :: Linux
Classifier: Operating System :: MacOS :: MacOS X
Classifier: Operating System :: Microsoft :: Windows :: Windows 10
Requires-Python: >=3.6
Requires-Dist: arrow (==0.13.1)
Requires-Dist: fastcache (==1.0.2)
Requires-Dist: psycopg2-binary (==2.8)
Requires-Dist: python-dateutil (==2.8.0)
Requires-Dist: pyyaml (==5.1)
Requires-Dist: requests (==2.21.0)
